[
    { "title": "Director(s)", "jobs": ["Director"] },
    { "title": "Producers", "jobs": ["Producer"] },
    { "title": "Writers", "jobs": ["Writer", "Screenplay"] },
    { "title": "Casting", "jobs": ["Casting"] },
    { "title": "Editor(s)", "jobs": ["Editor"] },
    { "title": "Cinematography", "jobs": ["Director of Photography", "Cinematography"] },
    { "title": "Assistant Directors", "jobs": ["Assistant Director"] },
    { "title": "Executive Producers", "jobs": ["Executive Producer"] },
    { "title": "Lighting", "jobs": ["Gaffer", "Lighting"] },
    { "title": "Camera Operator(s)", "jobs": ["Camera Operator"] },
    { "title": "Additional Photography", "jobs": ["Additional Photography"] },
    { "title": "Production Design", "jobs": ["Production Design"] },
    { "title": "Art Direction", "jobs": ["Art Direction"] },
    { "title": "Set Decoration", "jobs": ["Set Decoration"] },
    { "title": "Special Effects", "jobs": ["Special Effects"] },
    { "title": "Visual Effects", "jobs": ["Visual Effects"] },
    { "title": "Stunts", "jobs": ["Stunt Coordinator", "Stunts"] },
    { "title": "Composers", "jobs": ["Original Music Composer", "Composer"] },
    { "title": "Songs", "jobs": ["Songs"] },
    { "title": "Sound", "jobs": ["Sound", "Sound Designer", "Sound Editor", "Sound Mixer"] },
    { "title": "Costume Design", "jobs": ["Costume Designer"] },
    { "title": "Makeup", "jobs": ["Makeup Department"] },
    { "title": "Hairstyling", "jobs": ["Hairstyling"] }
]